{
  "play": {
    "play_id": "03060001",
    "title": "封丘大战",
    "aliases": [],
    "collection_id": "03000000",
    "collection_name": "《京剧汇编》",
    "collection_remark": "《京剧汇编》",
    "pdf_path": "赛题1-I京剧数据集/京剧剧本/03000000/03060001_封丘大战.pdf",
    "source_url": "http://scripts.xikao.com/play/03060001",
    "source_date": "2018-08-23",
    "page_count": 7,
    "file_size_bytes": 392299,
    "parse_error": null
  },
  "pages": [
    {
      "page_no": 1,
      "raw_line_count": 48,
      "body_lines": [
        "《封丘大战》",
        "主要角色",
        "史彦超：老生",
        "高行周：净",
        "情节",
        "苏逢吉谗害史弘肇。史弘肇弟史彦超镇守封丘，其子携仆投之。大将高行周奉命往攻，封丘城破，史氏全家",
        "自尽，史彦超败阵，突围而逃。",
        "根据《京剧汇编》第六十集：李万春藏本整理",
        "【第一场】",
        "（高怀德、高怀亮、王皇、刘闵同上，同起霸。）",
        "高怀德、",
        "高怀亮、",
        "王皇、",
        "刘闵　　　（同白）　　　　俺——",
        "高怀德　　（白）　　　　　高怀德。",
        "高怀亮　　（白）　　　　　高怀亮。",
        "王皇　　　（白）　　　　　王皇。",
        "刘闵　　　（白）　　　　　刘闵。",
        "高怀德　　（白）　　　　　众位将军请了！",
        "高怀亮、",
        "王皇、",
        "刘闵　　　（同白）　　　　请了！",
        "高怀德　　（白）　　　　　父帅升帐，你我两厢伺候！",
        "高怀亮、",
        "王皇、",
        "刘闵　　　（同白）　　　　请！",
        "（四龙套、高行周同上。）",
        "高行周　　（点绛唇）　　　奉命点将，威风浩荡，中军帐，摆列刀枪，要把封丘荡！",
        "高怀德、",
        "高怀亮、",
        "王皇、",
        "刘闵　　　（同白）　　　　参见父帅！",
        "高行周　　（白）　　　　　站立两厢！",
        "高怀德、",
        "高怀亮、",
        "王皇、",
        "刘闵　　　（同白）　　　　啊！",
        "高行周　　（念）　　　　　父子三人威风凛，冲锋破敌建功勋。奉命扫荡封丘郡，擒捉彦超方称心。",
        "　　　　　（白）　　　　　本帅、高行周。奉命捉拿归德节度使史彦超，因此统兵前来。昨日远探报到，",
        "　　　　　　　　　　　　　此处离归德不远，必须倍道而行，攻其不备。",
        "　　　　　　　　　　　　　怀德、怀亮，吩咐大小三军，拔营起寨，速速趱行！",
        "高怀德、",
        "高怀亮　　（同白）　　　　啊！",
        "　　　　　　　　　　　　　众将官，拔营起寨，速速趱行！",
        "众人　　　（同白）　　　　啊！",
        "（〖牌子〗。众人同下。）"
      ]
    },
    {
      "page_no": 2,
      "raw_line_count": 52,
      "body_lines": [
        "【第二场】",
        "李崇矩　　（内白）　　　　走哇！",
        "（李崇矩、史耀先同上。）",
        "李崇矩　　（唱）　　　　　恼恨奸贼心太狠，",
        "史耀先　　（唱）　　　　　苦害我一家为何情？",
        "　　　　　（白）　　　　　哎呀老哥哥呀！你我主仆逃出府来，投奔哪里安身才是？",
        "李崇矩　　（白）　　　　　公子，想那二老爷现在归德，统兵镇守。你我主仆投奔那里，一来报信，二来",
        "　　　　　　　　　　　　　也好让二老爷作一准备。",
        "史耀先　　（白）　　　　　老哥哥说得极是。你我急速前去便了！",
        "　　　　　（唱）　　　　　含悲忍泪把路上，",
        "李崇矩　　（唱）　　　　　见了那二老爷细说端详。",
        "（李崇矩、史耀先同下。）",
        "【第三场】",
        "（四龙套、中军、史彦超同上。）",
        "史彦超　　（引子）　　　　豪气冲霄汉，法森严，保主江山。",
        "　　　　　（念）　　　　　秋草初黄杀气多，腥风血漠动干戈。龙蛇蟠绕旌旗列，霜雪凝冰剑戟磨。",
        "　　　　　（白）　　　　　本镇、史彦超。北汉为臣，官拜归德节度。兄长弘肇，在朝奉君。只因边邻不",
        "　　　　　　　　　　　　　靖，日日操演兵将，以防不测。这几日本镇心惊肉跳，不知为了何事？",
        "（风旗上，过场，下。）",
        "史彦超　　（白）　　　　　啊，帅字旗无风自动，其中必有军情。",
        "　　　　　　　　　　　　　站堂军，伺候了！",
        "四龙套　　（同白）　　　　啊！",
        "（李崇矩、史耀先同上。）",
        "李崇矩、",
        "史耀先　　（同白）　　　　门上哪位在？",
        "中军　　　（白）　　　　　什么人？",
        "李崇矩　　（白）　　　　　烦劳通禀，就说帅爷的侄公子求见。",
        "中军　　　（白）　　　　　候着。",
        "（中军向史彦超。）",
        "中军　　　（白）　　　　　启禀帅爷：府门以外，有一老仆，手拉幼童，口称是帅爷的侄公子。",
        "史彦超　　（白）　　　　　叫他进来！",
        "中军　　　（白）　　　　　有请公子！",
        "（史耀先、李崇矩同进门。）",
        "史耀先　　（白）　　　　　唉，叔父哇！",
        "（史耀先哭。）",
        "史彦超　　（白）　　　　　为何这等模样？",
        "李崇矩　　（白）　　　　　哎呀二老爷呀！只因我家大老爷奏本谏君，那后主非但不听，反将大老爷与太",
        "　　　　　　　　　　　　　夫人一家老幼同斩市曹！",
        "史彦超　　（白）　　　　　你怎么讲？",
        "李崇矩　　（白）　　　　　问斩市曹！",
        "史彦超　　（三叫头）　　　母亲！兄长！唉，娘呀！",
        "　　　　　（唱）　　　　　听一言不由我魂消魄化，",
        "　　　　　（三叫头）　　　母亲！兄长！唉，娘呀！",
        "　　　　　（唱）　　　　　只气得史彦超咬碎银牙。",
        "　　　　　　　　　　　　　回头来便把那昏王叫骂，",
        "　　　　　　　　　　　　　可叹我一家人命染黄沙。",
        "李崇矩　　（白）　　　　　二老爷呀！",
        "　　　　　（唱）　　　　　这件事虽是那后主作差，",
        "　　　　　　　　　　　　　内有个苏逢吉暗把计发。",
        "史彦超　　（白）　　　　　好贼子！"
      ]
    },
    {
      "page_no": 3,
      "raw_line_count": 51,
      "body_lines": [
        "　　　　　（唱）　　　　　苏逢吉老奸贼真真胆大，",
        "　　　　　　　　　　　　　有什么冤与仇要害全家？",
        "　　　　　　　　　　　　　手拉娇儿大堂下，",
        "　　　　　　　　　　　　　快请夫人说根芽。",
        "中军　　　（白）　　　　　有请夫人！",
        "（丫鬟、史夫人同上。）",
        "史夫人　　（唱）　　　　　每日里在后堂香烧佛念，",
        "　　　　　　　　　　　　　但愿得吾老爷禄位高迁。",
        "　　　　　　　　　　　　　小丫鬟报一信二堂来见，",
        "　　　　　（白）　　　　　呀！",
        "　　　　　（唱）　　　　　为什么皱双眉泪洒胸前？",
        "　　　　　　　　　　　　　走向前道万福躬身下站，",
        "　　　　　　　　　　　　　尊老爷呼唤我所为哪般？",
        "史彦超　　（唱）　　　　　夫人有所不知情，",
        "　　　　　　　　　　　　　下官言来听分明：",
        "　　　　　　　　　　　　　长兄金殿去奏本，",
        "　　　　　　　　　　　　　逢吉老贼把计生。",
        "　　　　　　　　　　　　　昏王传旨将全家斩，",
        "　　　　　　　　　　　　　连累了年迈的娘亲命归阴。",
        "　　　　　　　　　　　　　我一家无故遭毒狠，",
        "　　　　　　　　　　　　　幸喜逃出这条根。",
        "史夫人　　（唱）　　　　　老爷不必两泪淋，",
        "　　　　　　　　　　　　　就该发兵报冤情。",
        "史彦超　　（白）　　　　　好哇！",
        "　　　　　（唱）　　　　　听一言来心猛省，",
        "　　　　　　　　　　　　　大丈夫不如女钗裙！",
        "　　　　　　　　　　　　　夫人且把二堂进！",
        "（史夫人、丫鬟同下。）",
        "史彦超　　（白）　　　　　中军！",
        "　　　　　（唱）　　　　　拿我令箭到各营。",
        "　　　　　　　　　　　　　就说是爷要兴人马！",
        "中军　　　（白）　　　　　啊！",
        "（史彦超、史耀先同下。）",
        "中军　　　（白）　　　　　各营将官听者：元帅有令，命你等全身披挂，齐至校场听点！",
        "四龙套　　（同白）　　　　啊！",
        "（众人同下。）",
        "【第四场】",
        "（四龙套、高怀德、高怀亮、王皇、刘闵、高行周同上。）",
        "高行周　　（白）　　　　　前道为何不行？",
        "众人　　　（同白）　　　　前面已是归德境界。",
        "高行周　　（白）　　　　　人马列开！好一处平川之所，就在此处安营扎寨，歇兵三日，前去攻城！",
        "众人　　　（同白）　　　　啊！",
        "（〖牌子〗。众人同下。）",
        "【第五场】",
        "探子　　　（内白）　　　　马来！",
        "（探子上。）",
        "探子　　　（念）　　　　　探子奉将令，四路探军情。",
        "　　　　　（白）　　　　　俺、史元帅帐下得力探子是也。今有高行周奉旨统兵数万，攻取归德。不免报",
        "　　　　　　　　　　　　　与主帅知道便了！"
      ]
    },
    {
      "page_no": 4,
      "raw_line_count": 51,
      "body_lines": [
        "（探子下。）",
        "【第六场】",
        "（四龙套、中军、史彦超同上。）",
        "史彦超　　（念）　　　　　柱石功勋凭三略，大将横行十万师。台上霜威凌草木，军中杀气燕飞迟。",
        "　　　　　（白）　　　　　本帅、史彦超。只因兄长奏本谏君，被昏王将吾全家问斩市曹，为此点动人马，",
        "　　　　　　　　　　　　　要与母、兄报仇。正是：",
        "　　　　　（念）　　　　　怒气冲霄汉，兴师报仇冤！",
        "探子　　　（内白）　　　　马来！",
        "（探子上。）",
        "探子　　　（念）　　　　　打探军情事，报与主帅知。",
        "　　　　　（白）　　　　　报！探子告进！元帅在上，探子参！",
        "史彦超　　（白）　　　　　有何军情？起来讲！",
        "探子　　　（白）　　　　　元帅容禀！",
        "　　　　　（念）　　　　　探子领将令，四路去打听：行周领人马，夺取归德城！",
        "史彦超　　（白）　　　　　那贼兵势如何？",
        "探子　　　（白）　　　　　那贼兵势浩荡，一路之上，好不威严人也！",
        "（〖牌子〗。）",
        "史彦超　　（白）　　　　　赏你银牌一面，再去打探！",
        "探子　　　（白）　　　　　得令！",
        "（探子下。）",
        "史彦超　　（白）　　　　　且住！时才探子报道：高行周统兵前来。我不免去至敌楼，观其动静便了。",
        "　　　　　　　　　　　　　众将官，敌楼去者！",
        "四龙套　　（同白）　　　　啊！",
        "史彦超　　（唱）　　　　　谗臣当道朝纲乱，",
        "　　　　　　　　　　　　　恨昏王无道听信谗言。",
        "　　　　　　　　　　　　　兄长金殿把本谏，",
        "　　　　　　　　　　　　　逢吉老贼他暗使巧机关。",
        "　　　　　　　　　　　　　害得我一家市曹斩，",
        "　　　　　　　　　　　　　白发老娘命染黄泉。",
        "　　　　　　　　　　　　　此一番统兵去交战，",
        "　　　　　　　　　　　　　拿住老贼活祭在灵前。",
        "　　　　　　　　　　　　　饮尔血，食尔肉，抽尔筋，剥尔皮，把尔的眼挖穿！",
        "　　　　　　　　　　　　　人来与爷往前赶！",
        "四龙套　　（同白）　　　　啊！",
        "（四龙套同下。）",
        "史彦超　　（唱）　　　　　到敌楼观动静细说根源。",
        "（史彦超、中军同下。）",
        "【第七场】",
        "高行周　　（内唱）　　　　奉命扫灭归德郡！",
        "（四龙套、高怀德、高怀亮、王皇、刘闵、高行周同上。）",
        "高行周　　（唱）　　　　　人强马壮似天神。",
        "　　　　　　　　　　　　　大队人马往前进，",
        "　　　　　　　　　　　　　大叫彦超快出城！",
        "史彦超　　（内唱）　　　　恨昏王无道贪色酒，",
        "（场上设城。四龙套、史彦超同上城。）",
        "史彦超　　（哭头）　　　　娘啊！",
        "　　　　　（唱）　　　　　叹慈颜不由人珠泪双流。",
        "　　　　　　　　　　　　　耳边厢又听得人喧马吼，",
        "　　　　　　　　　　　　　旌旗招展光射斗牛。"
      ]
    },
    {
      "page_no": 5,
      "raw_line_count": 51,
      "body_lines": [
        "　　　　　　　　　　　　　高行周坐雕鞍威风抖擞，",
        "　　　　　　　　　　　　　众儿郎似虎狼神鬼皆愁。",
        "　　　　　　　　　　　　　两边的众将士欲起争斗，",
        "　　　　　　　　　　　　　含悲忍泪说从头：",
        "　　　　　　　　　　　　　可叹我一家遭毒手，",
        "　　　　　　　　　　　　　年迈兄长血溅刀头。",
        "　　　　　　　　　　　　　为国忠良不长久，",
        "　　　　　　　　　　　　　俺情愿一死报冤仇。",
        "　　　　　　　　　　　　　劝尔等及早卸甲胄，",
        "　　　　　　　　　　　　　倘若迟延命难留。",
        "高行周　　（唱）　　　　　你兄长金殿把本奏，",
        "　　　　　　　　　　　　　毁谤君王是何由？",
        "　　　　　　　　　　　　　及早开城来献首，",
        "　　　　　　　　　　　　　免得某家用机谋。",
        "史彦超　　（白）　　　　　呸！",
        "　　　　　（唱）　　　　　奸贼休要夸海口，",
        "　　　　　　　　　　　　　不由彦超怒心头。",
        "　　　　　　　　　　　　　众将开城来争斗！",
        "四龙套　　（同白）　　　　啊！",
        "（史彦超、四龙套同出城，起打。高行周、四龙套、高怀德、高怀亮、王皇、刘闵同败下，史彦超、四龙套",
        "同追下。）",
        "【第八场】",
        "（四龙套、高怀德、高怀亮、王皇、刘闵、高行周同上。）",
        "高行周　　（白）　　　　　且住！史彦超来得厉害，这便如何是好？啊呵有了，想他人马俱在城外，城内",
        "　　　　　　　　　　　　　必然空虚。我不免诈开城池，杀他个措手不及。",
        "　　　　　　　　　　　　　众将官，诈城去者！",
        "众人　　　（同白）　　　　啊！",
        "（众人同走圆场。场上设城，守城兵上。）",
        "高行周　　（白）　　　　　上前叫城！",
        "众人　　　（同白）　　　　呔，开城！",
        "守城兵　　（白）　　　　　什么人？",
        "众人　　　（同白）　　　　元帅得胜回城。",
        "守城兵　　（白）　　　　　开城！",
        "（城门开。）",
        "高行周　　（白）　　　　　杀！",
        "众人　　　（同白）　　　　啊！",
        "（高行周、四龙套、高怀德、高怀亮、王皇、刘闵同进城，同走圆场。）",
        "高行周　　（白）　　　　　怀德、怀亮，命你二人，带领王皇、刘闵，去至封丘，四路埋伏，史彦超到来，",
        "　　　　　　　　　　　　　一齐杀出，不得有误！",
        "高怀德、",
        "高怀亮、",
        "王皇、",
        "刘闵　　　（同白）　　　　得令！",
        "（高怀德、高怀亮、王皇、刘闵同下。）",
        "高行周　　（白）　　　　　众将官，随爷杀奔帅府去者！",
        "四龙套　　（同白）　　　　啊！",
        "（众人同下。）",
        "【第九场】",
        "（史夫人、史小姐同上。）"
      ]
    },
    {
      "page_no": 6,
      "raw_line_count": 49,
      "body_lines": [
        "史夫人　　（唱）　　　　　老爷出兵无音信，",
        "　　　　　　　　　　　　　倒叫妾身挂在心。",
        "　　　　　　　　　　　　　手拉姣儿二堂进，",
        "　　　　　　　　　　　　　但听家院报分明。",
        "李崇矩　　（内白）　　　　走哇！",
        "（李崇矩上。）",
        "李崇矩　　（唱）　　　　　适才府前得一信，",
        "　　　　　　　　　　　　　行周领兵诈开城。",
        "　　　　　　　　　　　　　迈步且把二堂进，",
        "　　　　　　　　　　　　　再与夫人说分明。",
        "　　　　　（白）　　　　　哎呀夫人，大事不好了！",
        "史夫人　　（白）　　　　　何事惊慌？",
        "李崇矩　　（白）　　　　　那贼诈开城池，眼看杀到府门来了！",
        "史夫人　　（白）　　　　　哎呀！",
        "　　　　　（唱）　　　　　听一言来胆战惊，",
        "　　　　　　　　　　　　　奸贼杀奔帅府门。",
        "（〖急急风〗。四龙套、高行周同上。史夫人、史小姐同自刎。）",
        "高行周　　（白）　　　　　众将官，四门换了“高”字旗号，带了他妻儿的人头，随爷敌楼去者！",
        "四龙套　　（同白）　　　　啊！",
        "（众人同下。）",
        "【第十场】",
        "（〖急急风〗。八大刀手、高怀德、高怀亮、王皇、刘闵同上，过场，同下。）",
        "【第十一场】",
        "（四龙套、马童、史彦超同上，望城。四龙套、高行周同上城，丢人头。史彦超痛倒。八大刀手、高怀德、",
        "高怀亮、王皇、刘闵同上，同起打。高怀德杀死马童，史彦超、四龙套同败下。高怀德、高怀亮、王皇、刘",
        "闵、八大刀手同追下。）",
        "【第十二场】",
        "史彦超　　（内唱）　　　　人困马乏难交阵！",
        "（四龙套、史彦超同上。）",
        "史彦超　　（唱）　　　　　可叹我史彦超、忠直耿耿为国一片心，恨昏王，信奸佞，连累了白发老娘、一",
        "　　　　　　　　　　　　　家大小受典刑，我好不伤情！",
        "　　　　　　　　　　　　　叹兄长捐躯把忠尽，",
        "　　　　　　　　　　　　　因此上为报仇才动刀兵。",
        "　　　　　　　　　　　　　俺这里勒战马疆场来进！",
        "（高怀德上。）",
        "高怀德　　（白）　　　　　哪里走？",
        "　　　　　（唱）　　　　　催动战马喊杀声。",
        "史彦超　　（唱）　　　　　问声来将名和姓？",
        "高怀德　　（唱）　　　　　高怀德就是我的名。",
        "史彦超　　（唱）　　　　　有何本领敢上阵？",
        "高怀德　　（唱）　　　　　你敢杀？",
        "史彦超　　（唱）　　　　　你敢战？",
        "高怀德　　（白）　　　　　看枪！",
        "史彦超　　（唱）　　　　　管叫你弃甲丢盔、走投无路丧残生！",
        "（高怀德、史彦超同起打。四龙套同下，高怀德败下。）",
        "史彦超　　（唱）　　　　　见来将败了阵心中欢庆，",
        "（高怀亮上。）"
      ]
    },
    {
      "page_no": 7,
      "raw_line_count": 31,
      "body_lines": [
        "高怀亮　　（白）　　　　　哪里走？",
        "　　　　　（唱）　　　　　青铜宝刀发光明。",
        "史彦超　　（唱）　　　　　你是何人敢交阵？",
        "高怀亮　　（唱）　　　　　高怀亮就是我的名。",
        "史彦超　　（唱）　　　　　无名小将休夸口，",
        "　　　　　　　　　　　　　比一比谁胜与谁能？",
        "（高怀亮、史彦超同起打。高怀亮败下。）",
        "史彦超　　（唱）　　　　　催坐骑在阵前用目观定：",
        "　　　　　　　　　　　　　眼见得旌旗招展、杀气腾腾、尘埃滚滚、战鼓齐鸣、见二将好似天神。",
        "（王皇、刘闵同上。）",
        "王皇　　　（唱）　　　　　骑一匹乌骓马威风凛凛，",
        "刘闵　　　（唱）　　　　　手提着素银枪鬼惧神惊。",
        "史彦超　　（唱）　　　　　勒马停蹄来观定，",
        "　　　　　　　　　　　　　两员将打扮得盔缨璨烂铠甲鲜明。",
        "王皇、",
        "刘闵　　　（同唱）　　　　叫一声史彦超及早归顺，",
        "史彦超　　（唱）　　　　　金枪一抖管叫你命丧残生！",
        "（史彦超、王皇、刘闵同起打。王皇、刘闵同败下。四龙套、八大刀手、高怀德、高怀亮、王皇、刘闵、高",
        "行周同上。）",
        "史彦超　　（唱）　　　　　霎时陷入迷魂阵，",
        "　　　　　　　　　　　　　四面俱是汉营兵。",
        "　　　　　　　　　　　　　左冲右挡无处奔！",
        "（史彦超败下。）",
        "众人　　　（同白）　　　　那贼大败！",
        "高行周　　（白）　　　　　败军之将，不可追赶。息兵三日，班师回朝！",
        "众人　　　（同白）　　　　啊！",
        "（众人同下。）",
        "（完）"
      ]
    }
  ]
}